alexandria/__init__.py
alexandria/alexandria_gui.py
alexandria/alexandria_ide.py
alexandria/console/__init__.py
alexandria/console/console_utilities.py
alexandria/datasets/__init__.py
alexandria/datasets/data_sets.py
alexandria/datasets/fdi.csv
alexandria/datasets/islm.csv
alexandria/datasets/taylor.csv
alexandria/graphics/__init__.py
alexandria/graphics/graphics.py
alexandria/graphics/graphics_utilities.py
alexandria/graphics/regression_graphics.py
alexandria/graphics/vector_autoregression_graphics.py
alexandria/interface/__init__.py
alexandria/interface/caret_left.png
alexandria/interface/caret_right.png
alexandria/interface/credits.png
alexandria/interface/default_input_interface.py
alexandria/interface/graphical_user_interface.py
alexandria/interface/no_graphic.png
alexandria/interface/python.png
alexandria/interface/run_button.png
alexandria/interface/tab1_interface.py
alexandria/interface/tab2_regression_interface.py
alexandria/interface/tab2_vec_varma_interface.py
alexandria/interface/tab2_vector_autoregression_interface.py
alexandria/interface/tab3_interface.py
alexandria/interface/tab4_interface.py
alexandria/interface/tab5_interface.py
alexandria/linear_regression/__init__.py
alexandria/linear_regression/autocorrelated_bayesian_regression.py
alexandria/linear_regression/bayesian_regression.py
alexandria/linear_regression/heteroscedastic_bayesian_regression.py
alexandria/linear_regression/hierarchical_bayesian_regression.py
alexandria/linear_regression/independent_bayesian_regression.py
alexandria/linear_regression/linear_regression.py
alexandria/linear_regression/main.py
alexandria/linear_regression/maximum_likelihood_regression.py
alexandria/linear_regression/regression_utilities.py
alexandria/linear_regression/simple_bayesian_regression.py
alexandria/math/__init__.py
alexandria/math/linear_algebra.py
alexandria/math/math_utilities.py
alexandria/math/random_number_generators.py
alexandria/math/stat_utilities.py
alexandria/processor/__init__.py
alexandria_python-2.0.1.dist-info/LICENSE
alexandria_python-2.0.1.dist-info/METADATA
alexandria_python-2.0.1.dist-info/WHEEL
alexandria_python-2.0.1.dist-info/top_level.txt
alexandria_python-2.0.1.dist-info/RECORD
